svGPFA/__init__.py
svGPFA/plot/__init__.py
svGPFA/plot/plotUtilsPlotly.py
svGPFA/simulations/__init__.py
svGPFA/simulations/simulations.py
svGPFA/simulations/utils.py
svGPFA/stats/__init__.py
svGPFA/stats/expectedLogLikelihood.py
svGPFA/stats/kernels.py
svGPFA/stats/kernelsMatricesStore.py
svGPFA/stats/klDivergence.py
svGPFA/stats/svEM.py
svGPFA/stats/svEmbedding.py
svGPFA/stats/svGPFAModelFactory.py
svGPFA/stats/svLBFGS.py
svGPFA/stats/svLowerBound.py
svGPFA/stats/svPosteriorOnIndPoints.py
svGPFA/stats/svPosteriorOnLatents.py
svGPFA/utils/__init__.py
svGPFA/utils/configUtils.py
svGPFA/utils/initUtils.py
svGPFA/utils/miscUtils.py
svGPFA/utils/my_globals.py
svGPFA/utils/test.py
svGPFA-1.0.1.dist-info/LICENSE
svGPFA-1.0.1.dist-info/METADATA
svGPFA-1.0.1.dist-info/WHEEL
svGPFA-1.0.1.dist-info/top_level.txt
svGPFA-1.0.1.dist-info/RECORD
