Metadata-Version: 2.1
Name: svGPFA
Version: 1.0.1
Summary: Python implementation of the svGPFA algorithm (Duncker and Sahani, 2018)
Home-page: https://github.com/joacorapela/svGPFA
Author: Joaquin Rapela
Author-email: j.rapela@ucl.ac.uk
License: MIT
Classifier: License :: OSI Approved :: MIT License
Classifier: Programming Language :: Python :: 3.7
License-File: LICENSE
Requires-Dist: gcnu-common
Requires-Dist: torch
Requires-Dist: scipy
Provides-Extra: docs
Requires-Dist: sphinx-gallery ; extra == 'docs'
Provides-Extra: notebook
Requires-Dist: notebook ; extra == 'notebook'
Requires-Dist: pandas ; extra == 'notebook'
Requires-Dist: plotly ; extra == 'notebook'
Requires-Dist: kaleido ; extra == 'notebook'
Requires-Dist: scikit-learn ; extra == 'notebook'
